Workbook

Sheet monthly_sales_by_category
A1: month | B1: category | C1: total_sales | D1: total_profit | E1: order_count
A2: 43466 | B2: Furniture | C2: 7696.683 | D2: 332.2275 | E2: 18 | G2: Quarter | H2: Total revenue | I2: QoQ Growth % | L2: quarterly total-revenue summary | M2: =SUMIFS(C:C, A:A, ">="&DATE(2019,1,1), A:A, "<"&DATE(2019,4,1)) -> 90311.121
A3: 43466 | B3: Office Supplies | C3: 5299.682 | D3: 1604.4712 | E3: 32 | G3: Q1 2019 | H3: =SUMIFS(C:C, A:A, ">="&DATE(2019,1,1), A:A, "<"&DATE(2019,4,1)) -> 90311.121
A4: 43466 | B4: Technology | C4: 5620.066 | D4: 916.3914 | E4: 16 | G4: Q2 2019 | H4: =SUMIFS(C:C, A:A, ">="&DATE(2019,4,1), A:A, "<"&DATE(2019,7,1)) -> 130082.3 | I4: =(H4-H3)/H3 -> 0.44037965
A5: 43497 | B5: Furniture | C5: 3925.551 | D5: 377.0352 | E5: 17 | G5: Q3 2019 | H5: =SUMIFS(C:C, A:A, ">="&DATE(2019,7,1), A:A, "<"&DATE(2019,10,1)) -> 143787.36 | I5: =(H5-H4)/H4 -> 0.10535685
A6: 43497 | B6: Office Supplies | C6: 7794.35 | D6: 1330.0009 | E6: 31 | G6: Q4 2019 | H6: =SUMIFS(C:C, A:A, ">="&DATE(2019,10,1), A:A, "<"&DATE(2020,1,1)) -> 200498.75 | I6: =(H6-H5)/H5 -> 0.39441152
A7: 43497 | B7: Technology | C7: 8258.914 | D7: 3297.5434 | E7: 13 | G7: Q1 2020 | H7: =SUMIFS(C:C, A:A, ">="&DATE(2020,1,1), A:A, "<"&DATE(2020,4,1)) -> 171060.86 | I7: =(H7-H6)/H6 -> -0.14682332
A8: 43525 | B8: Furniture | C8: 12801.092 | D8: -555.268 | E8: 38 | G8: Q2 2020 | H8: =SUMIFS(C:C, A:A, ">="&DATE(2020,4,1), A:A, "<"&DATE(2020,7,1)) -> 186800.37 | I8: =(H8-H7)/H7 -> 0.092011181
A9: 43525 | B9: Office Supplies | C9: 17346.931 | D9: 1061.4056 | E9: 57 | G9: Q3 2020 | H9: =SUMIFS(C:C, A:A, ">="&DATE(2020,7,1), A:A, "<"&DATE(2020,10,1)) -> 257219.96 | I9: =(H9-H8)/H8 -> 0.37697775
A10: 43525 | B10: Technology | C10: 21567.852 | D10: 3105.8304 | E10: 31 | G10: Q4 2020 | H10: =SUMIFS(C:C, A:A, ">="&DATE(2020,10,1), A:A, "<"&DATE(2021,1,1)) -> 386043.6 | I10: =(H10-H9)/H9 -> 0.50083066
A11: 43556 | B11: Furniture | C11: 13212.09 | D11: 364.8334 | E11: 33
A12: 43556 | B12: Office Supplies | C12: 10647.447 | D12: -1100.4821 | E12: 66
A13: 43556 | B13: Technology | C13: 14890.502 | D13: 3713.4636 | E13: 21
A14: 43586 | B14: Furniture | C14: 15119.835 | D14: 1824.4739 | E14: 38
A15: 43586 | B15: Office Supplies | C15: 13035.202 | D15: 2397.5024 | E15: 84
A16: 43586 | B16: Technology | C16: 22832.691 | D16: 4440.1701 | E16: 32
A17: 43617 | B17: Furniture | C17: 13070.572 | D17: -106.2665 | E17: 30
A18: 43617 | B18: Office Supplies | C18: 10901.81 | D18: 2467.4894 | E18: 67
A19: 43617 | B19: Technology | C19: 16372.152 | D19: 2389.1552 | E19: 30
A20: 43647 | B20: Furniture | C20: 13068.519 | D20: 1038.9073 | E20: 29
A21: 43647 | B21: Office Supplies | C21: 12924.444 | D21: 1123.9602 | E21: 75
A22: 43647 | B22: Technology | C22: 13269 | D22: 2270.0104 | E22: 28
... A73: 44166 | B73: Technology | C73: 26361.91 | D73: 5562.2788 | E73: 63

Sheet Assumptions
B2: Base quarterly growth rate | C2: =AVERAGE(monthly_sales_by_category!I4:I10) -> 0.25187776
B3: Best-case adjustment | C3: 0
B4: Worst-case adjustment | C4: -0.05
B5: Last known quarter revenue | C5: =monthly_sales_by_category!H10 -> 386043.6

Sheet Forecast
A1: Scenario | B1: Projected Q1 2021 Revenue
A2: Base Case | B2: =Assumptions!C5*(1+Assumptions!C2) -> 483279.39
A3: Best Case | B3: =Assumptions!C5*(1+Assumptions!C2+Assumptions!C3) -> 483279.39
A4: Worst Case | B4: =Assumptions!C5*(1+Assumptions!C2+Assumptions!C4) -> 463977.21
